snippets2changelog/__init__.py
snippets2changelog/cli.py
snippets2changelog/collector.py
snippets2changelog/common.py
snippets2changelog/creator.py
snippets2changelog/parser.py
snippets2changelog/templates/changelog.md.template
snippets2changelog/templates/changelog_part.md.template
snippets2changelog/templates/snippet.md.template
snippets2changelog/version.py
snippets2changelog-1.6.0.dist-info/LICENSE.txt
snippets2changelog-1.6.0.dist-info/METADATA
snippets2changelog-1.6.0.dist-info/WHEEL
snippets2changelog-1.6.0.dist-info/entry_points.txt
snippets2changelog-1.6.0.dist-info/RECORD
