Metadata-Version: 2.1
Name: snippets2changelog
Version: 1.6.0
Summary: Generate a changelog from individual snippets
Home-page: https://github.com/brainelectronics/snippets2changelog
License: MIT
Author: brainelectronics
Author-email: info@brainelectronics.de
Requires-Python: >=3.9,<4.0
Classifier: Development Status :: 5 - Production/Stable
Classifier: Intended Audience :: Developers
Classifier: License :: OSI Approved :: MIT License
Classifier: Programming Language :: Python :: 3
Classifier: Programming Language :: Python :: 3.9
Classifier: Programming Language :: Python :: 3.10
Classifier: Programming Language :: Python :: 3.11
Classifier: Programming Language :: Python :: 3.12
Classifier: Programming Language :: Python :: 3.13
Classifier: Programming Language :: Python :: 3 :: Only
Classifier: Topic :: Software Development :: Build Tools
Classifier: Topic :: Software Development :: Version Control
Requires-Dist: GitPython (>=3.1.43,<3.2.0)
Requires-Dist: changelog2version (>=0.10,<1)
Requires-Dist: jinja2 (>=3.1.4,<4.0.0)
Requires-Dist: pyyaml (>=6.0,<6.1)
Project-URL: Repository, https://github.com/brainelectronics/snippets2changelog
